pygame_easy_btn/__init__.py
pygame_easy_btn/button.py
pygame_easy_btn-1.0.3.dist-info/METADATA
pygame_easy_btn-1.0.3.dist-info/WHEEL
pygame_easy_btn-1.0.3.dist-info/top_level.txt
pygame_easy_btn-1.0.3.dist-info/RECORD
