Metadata-Version: 2.1
Name: pygame-easy-btn
Version: 1.0.3
Summary: python package for pygame to make buttons
Author: Amin shahrabi
Author-email: shahrabiamin70@gmail.com
License: Apache License 2.0
Platform: UNKNOWN
Requires-Dist: pygame
